{"duration": 900, "start_time": "asap 2025-05-16 15:20", "binaries": [{"hardware": "firefly", "bin_file": "contikimac32Hz-conservative.bin", "targets": [1, 2, 3, 4, 5, 6, 7, 8, 9, 10, 11, 12, 13, 14, 15, 16, 17, 18, 19, 20, 21, 22, 23, 24, 25, 26, 27, 28, 29, 30, 31, 32, 33, 34, 35, 36], "programAddress": "0x00200000", "serialBaudrate": null, "tmp_usertt": false, "tmp_useusb": false}], "email": null, "island": "DEPT", "logs": 0, "required": "all", "snapshot": false, "test_id": 39013, "user": "damiano.salvaterra@studenti.unitn.it"}